Workbook

Sheet Assumptions
A1: Data Center Capital Project Investment Model
A2: Sourced from Digital Realty Trust (DLR) FY2025 / Q4 2025 public disclosures; applied to a hypothetical 50 MW development
A4: Development & Market Assumptions
A6: Project size (MW, IT load) | B6: 50 | E6: Source: Illustrative project sized against DLR's disclosed development pipeline
A7: Development cost per MW | B7: 13000000 | E7: Source: Source: DLR Q4 2025 results, $10.0B gross development pipeline value / 769 MW underway
A8: Total development CapEx | B8: =B6*B7 -> 650000000 | E8: Source: Calculated: Project size x cost per MW
A9: Construction period (months) | B9: 22 | E9: Source: Source: DLR Q4 2025 supplemental, typical hyperscale build cycle disclosed in pipeline commentary
A10: Pre-lease at delivery | B10: 0.75 | E10: Source: Source: DLR Q4 2025 results, 75% of Q4 deliveries were pre-leased
A11: Expected stabilized yield on cost | B11: 0.119 | E11: Source: Source: DLR Q4 2025 results, 11.9% expected stabilized yield on $10B pipeline
A12: Months to full stabilization post-delivery | B12: 18 | E12: Source: Illustrative lease-up ramp consistent with DLR disclosed absorption pace
A13: Target leverage (net debt / EBITDA) | B13: 5.5 | E13: Source: Source: DLR Q4 2025 results, long-term target leverage of 5.5x (actual 4.9x at YE2025)
A14: Assumed loan-to-cost (debt financing) | B14: 0.55 | E14: Source: Modeling assumption consistent with target leverage; adjust in sensitivity tab
A15: Assumed cost of debt (rate) | B15: 0.055 | E15: Source: General market assumption for investment-grade REIT secured/unsecured debt; confirm against live pricing before use
A16: Discount rate / cost of capital (WACC) | B16: 0.085 | E16: Source: General market assumption for data center development risk; confirm against live pricing before use
A17: Exit / stabilized cap rate | B17: 0.065 | E17: Source: General market assumption for stabilized hyperscale data center assets; confirm before use
A18: Hold period (years, post-stabilization) | B18: 5 | E18: Source: Illustrative hold period for return calculation
A20: Note: cells in blue are inputs. Cells flagged with a note are general market assumptions, not company-sourced, and should be confirmed before external use.

Sheet CapEx Timeline
A1: Construction CapEx Phasing (Months 1-24)
A2: Month | B2: 1 | C2: 2 | D2: 3 | E2: 4 | F2: 5 | G2: 6 | H2: 7 | I2: 8 | J2: 9 | K2: 10 | L2: 11 | M2: 12 | N2: 13 | O2: 14 | P2: 15 | Q2: 16 | R2: 17 | S2: 18 | T2: 19 | U2: 20 | V2: 21 | W2: 22 | X2: 23 | Y2: 24
A3: % of CapEx spent (S-curve) | B3: 0.01186 | C3: 0.02259 | D3: 0.03219 | E3: 0.04065 | F3: 0.048 | G3: 0.05421 | H3: 0.05929 | I3: 0.06324 | J3: 0.06606 | K3: 0.06776 | L3: 0.06832 | M3: 0.06776 | N3: 0.06606 | O3: 0.06324 | P3: 0.05929 | Q3: 0.05421 | R3: 0.048 | S3: 0.04065 | T3: 0.03219 | U3: 0.02259 | V3: 0.01186 | W3: 0 | X3: 0 | Y3: 0
A4: CapEx spent ($) | B4: =B3*Assumptions!$B$8 -> 7709000 | C4: =C3*Assumptions!$B$8 -> 14683500 | D4: =D3*Assumptions!$B$8 -> 20923500 | E4: =E3*Assumptions!$B$8 -> 26422500 | F4: =F3*Assumptions!$B$8 -> 31200000 | G4: =G3*Assumptions!$B$8 -> 35236500 | H4: =H3*Assumptions!$B$8 -> 38538500 | I4: =I3*Assumptions!$B$8 -> 41106000 | ... Y4: =Y3*Assumptions!$B$8 -> 0
A5: Cumulative CapEx ($) | B5: =B4 -> 7709000 | C5: =B5+C4 -> 22392500 | D5: =C5+D4 -> 43316000 | E5: =D5+E4 -> 69738500 | F5: =E5+F4 -> 100938500 | G5: =F5+G4 -> 136175000 | H5: =G5+H4 -> 174713500 | I5: =H5+I4 -> 215819500 | J5: =I5+J4 -> 258758500 | ... Y5: =X5+Y4 -> 650013000
A7: Total development CapEx (check) | B7: =SUM(B4:Y4) -> 650013000 | C7: should equal Assumptions total CapEx

Sheet Cash Flow & Returns
A1: Annual Cash Flow, Yield Build & Returns (Years 0-6)
A2: Year | B2: Yr 0 (Construction) | C2: Yr 1 | D2: Yr 2 | E2: Yr 3 | F2: Yr 4 | G2: Yr 5 | H2: Yr 6 (Exit)
A3: Development CapEx | B3: =-Assumptions!$B$8 -> -650000000 | C3: 0 | D3: 0 | E3: 0 | F3: 0 | G3: 0 | H3: 0
A4: Stabilized NOI (at full yield on cost) | B4: =Assumptions!$B$8*Assumptions!$B$11 -> 77350000
A5: Lease-up ramp (% of stabilized NOI achieved) | B5: 0 | C5: 0.4 | D5: 0.85 | E5: 1 | F5: 1 | G5: 1 | H5: 1
A6: NOI ($) | B6: =B5*$B$4 -> 0 | C6: =C5*$B$4 -> 30940000 | D6: =D5*$B$4 -> 65747500 | E6: =E5*$B$4 -> 77350000 | F6: =F5*$B$4 -> 77350000 | G6: =G5*$B$4 -> 77350000 | H6: =H5*$B$4 -> 77350000
A8: Debt drawn (at delivery) | B8: =Assumptions!$B$8*Assumptions!$B$14 -> 357500000
A9: Interest expense | B9: 0 | C9: =-$B$8*Assumptions!$B$15 -> -19662500 | D9: =-$B$8*Assumptions!$B$15 -> -19662500 | E9: =-$B$8*Assumptions!$B$15 -> -19662500 | F9: =-$B$8*Assumptions!$B$15 -> -19662500 | G9: =-$B$8*Assumptions!$B$15 -> -19662500 | H9: =-$B$8*Assumptions!$B$15 -> -19662500
A10: DSCR (NOI / interest expense) | B10: - | C10: =IF(C9=0,"-",C6/-C9) -> 1.5735537 | D10: =IF(D9=0,"-",D6/-D9) -> 3.3438017 | E10: =IF(E9=0,"-",E6/-E9) -> 3.9338843 | F10: =IF(F9=0,"-",F6/-F9) -> 3.9338843 | G10: =IF(G9=0,"-",G6/-G9) -> 3.9338843 | H10: =IF(H9=0,"-",H6/-H9) -> 3.9338843
A12: Unlevered free cash flow | B12: =B3+B6 -> -650000000 | C12: =C6 -> 30940000 | D12: =D6 -> 65747500 | E12: =E6 -> 77350000 | F12: =F6 -> 77350000 | G12: =G6 -> 77350000 | H12: =H6+(B4/Assumptions!$B$17) -> 1267350000
A14: Levered free cash flow | B14: =B3+B8 -> -292500000 | C14: =C6+C9 -> 11277500 | D14: =D6+D9 -> 46085000 | E14: =E6+E9 -> 57687500 | F14: =F6+F9 -> 57687500 | G14: =G6+G9 -> 57687500 | H14: =H6+H9+(B4/Assumptions!$B$17)-$B$8 -> 890187500
A16: Return Metrics
A17: Unlevered IRR | B17: =IRR(B12:H12) -> 0.18480469
A18: Levered IRR | B18: =IRR(B14:H14) -> 0.29084583
A19: Unlevered NPV (at WACC) | B19: =NPV(Assumptions!$B$16,C12:H12)+B12 -> 3.7899463e+08
A20: Payback period (years, undiscounted) | B20: =MATCH(TRUE(),INDEX(B5:H5>=1,0),0)-1+((1-C5)/(D5-C5)) -> 4.3333333 | C20: approximate, based on stabilization ramp

Sheet Sensitivity
A1: Sensitivity: Unlevered IRR vs. Stabilized Yield on Cost and Exit Cap Rate
A2: Each row rebuilds the full unlevered cash flow line at the stated yield/cap and computes IRR directly, base case highlighted
A4: Sensitivity A: Yield on Cost (exit cap held at base case)
A5: Yield on Cost | B5: Yr0 CapEx | C5: Yr1 NOI | D5: Yr2 NOI | E5: Yr3 NOI | F5: Yr4 NOI | G5: Yr5 NOI | H5: Yr6 NOI+Exit | I5: Unlevered IRR
A6: 0.099 | B6: =-Assumptions!$B$8 -> -650000000 | C6: ='Cash Flow & Returns'!C5*Assumptions!$B$8*A6 -> 25740000 | D6: ='Cash Flow & Returns'!D5*Assumptions!$B$8*A6 -> 54697500 | E6: ='Cash Flow & Returns'!E5*Assumptions!$B$8*A6 -> 64350000 | F6: ='Cash Flow & Returns'!F5*Assumptions!$B$8*A6 -> 64350000 | G6: =Assumptions!$B$8*A6 -> 64350000 | H6: =Assumptions!$B$8*A6+(Assumptions!$B$8*A6/Assumptions!$B$17) -> 1054350000 | I6: =IRR(B6:H6) -> 0.14333764
A7: 0.109 | B7: =-Assumptions!$B$8 -> -650000000 | C7: ='Cash Flow & Returns'!C5*Assumptions!$B$8*A7 -> 28340000 | D7: ='Cash Flow & Returns'!D5*Assumptions!$B$8*A7 -> 60222500 | E7: ='Cash Flow & Returns'!E5*Assumptions!$B$8*A7 -> 70850000 | F7: ='Cash Flow & Returns'!F5*Assumptions!$B$8*A7 -> 70850000 | G7: =Assumptions!$B$8*A7 -> 70850000 | H7: =Assumptions!$B$8*A7+(Assumptions!$B$8*A7/Assumptions!$B$17) -> 1160850000 | I7: =IRR(B7:H7) -> 0.16475945
A8: 0.119 | B8: =-Assumptions!$B$8 -> -650000000 | C8: ='Cash Flow & Returns'!C5*Assumptions!$B$8*A8 -> 30940000 | D8: ='Cash Flow & Returns'!D5*Assumptions!$B$8*A8 -> 65747500 | E8: ='Cash Flow & Returns'!E5*Assumptions!$B$8*A8 -> 77350000 | F8: ='Cash Flow & Returns'!F5*Assumptions!$B$8*A8 -> 77350000 | G8: =Assumptions!$B$8*A8 -> 77350000 | H8: =Assumptions!$B$8*A8+(Assumptions!$B$8*A8/Assumptions!$B$17) -> 1267350000 | I8: =IRR(B8:H8) -> 0.18480469
A9: 0.129 | B9: =-Assumptions!$B$8 -> -650000000 | C9: ='Cash Flow & Returns'!C5*Assumptions!$B$8*A9 -> 33540000 | D9: ='Cash Flow & Returns'!D5*Assumptions!$B$8*A9 -> 71272500 | E9: ='Cash Flow & Returns'!E5*Assumptions!$B$8*A9 -> 83850000 | F9: ='Cash Flow & Returns'!F5*Assumptions!$B$8*A9 -> 83850000 | G9: =Assumptions!$B$8*A9 -> 83850000 | H9: =Assumptions!$B$8*A9+(Assumptions!$B$8*A9/Assumptions!$B$17) -> 1373850000 | I9: =IRR(B9:H9) -> 0.20367701
A10: 0.139 | B10: =-Assumptions!$B$8 -> -650000000 | C10: ='Cash Flow & Returns'!C5*Assumptions!$B$8*A10 -> 36140000 | D10: ='Cash Flow & Returns'!D5*Assumptions!$B$8*A10 -> 76797500 | E10: ='Cash Flow & Returns'!E5*Assumptions!$B$8*A10 -> 90350000 | F10: ='Cash Flow & Returns'!F5*Assumptions!$B$8*A10 -> 90350000 | G10: =Assumptions!$B$8*A10 -> 90350000 | H10: =Assumptions!$B$8*A10+(Assumptions!$B$8*A10/Assumptions!$B$17) -> 1480350000 | I10: =IRR(B10:H10) -> 0.22153688
A13: Sensitivity B: Exit Cap Rate (yield on cost held at base case)
A14: Exit Cap Rate | B14: Yr0 CapEx | C14: Yr1 NOI | D14: Yr2 NOI | E14: Yr3 NOI | F14: Yr4 NOI | G14: Yr5 NOI | H14: Yr6 NOI+Exit | I14: Unlevered IRR
A15: 0.055 | B15: ='Cash Flow & Returns'!B12 -> -650000000 | C15: ='Cash Flow & Returns'!C12 -> 30940000 | D15: ='Cash Flow & Returns'!D12 -> 65747500 | E15: ='Cash Flow & Returns'!E12 -> 77350000 | F15: ='Cash Flow & Returns'!F12 -> 77350000 | G15: ='Cash Flow & Returns'!G12 -> 77350000 | H15: ='Cash Flow & Returns'!H6+(Assumptions!$B$8*Assumptions!$B$11/A15) -> 1.4837136e+09 | I15: =IRR(B15:H15) -> 0.21100684
A16: 0.06 | B16: ='Cash Flow & Returns'!B12 -> -650000000 | C16: ='Cash Flow & Returns'!C12 -> 30940000 | D16: ='Cash Flow & Returns'!D12 -> 65747500 | E16: ='Cash Flow & Returns'!E12 -> 77350000 | F16: ='Cash Flow & Returns'!F12 -> 77350000 | G16: ='Cash Flow & Returns'!G12 -> 77350000 | H16: ='Cash Flow & Returns'!H6+(Assumptions!$B$8*Assumptions!$B$11/A16) -> 1.3665167e+09 | I16: =IRR(B16:H16) -> 0.19719972
A17: 0.065 | B17: ='Cash Flow & Returns'!B12 -> -650000000 | C17: ='Cash Flow & Returns'!C12 -> 30940000 | D17: ='Cash Flow & Returns'!D12 -> 65747500 | E17: ='Cash Flow & Returns'!E12 -> 77350000 | F17: ='Cash Flow & Returns'!F12 -> 77350000 | G17: ='Cash Flow & Returns'!G12 -> 77350000 | H17: ='Cash Flow & Returns'!H6+(Assumptions!$B$8*Assumptions!$B$11/A17) -> 1267350000 | I17: =IRR(B17:H17) -> 0.18480469
A18: 0.07 | B18: ='Cash Flow & Returns'!B12 -> -650000000 | C18: ='Cash Flow & Returns'!C12 -> 30940000 | D18: ='Cash Flow & Returns'!D12 -> 65747500 | E18: ='Cash Flow & Returns'!E12 -> 77350000 | F18: ='Cash Flow & Returns'!F12 -> 77350000 | G18: ='Cash Flow & Returns'!G12 -> 77350000 | H18: ='Cash Flow & Returns'!H6+(Assumptions!$B$8*Assumptions!$B$11/A18) -> 1182350000 | I18: =IRR(B18:H18) -> 0.17359073
A19: 0.075 | B19: ='Cash Flow & Returns'!B12 -> -650000000 | C19: ='Cash Flow & Returns'!C12 -> 30940000 | D19: ='Cash Flow & Returns'!D12 -> 65747500 | E19: ='Cash Flow & Returns'!E12 -> 77350000 | F19: ='Cash Flow & Returns'!F12 -> 77350000 | G19: ='Cash Flow & Returns'!G12 -> 77350000 | H19: ='Cash Flow & Returns'!H6+(Assumptions!$B$8*Assumptions!$B$11/A19) -> 1.1086833e+09 | I19: =IRR(B19:H19) -> 0.16337756

Sheet Executive Summary
A1: Executive Summary: 50 MW Data Center Development
A2: Prepared as a capital project investment case study, assumptions sourced from Digital Realty Trust (DLR) public FY2025 disclosures
A4: Key Metrics
A5: Total development CapEx | B5: =Assumptions!$B$8 -> 650000000
A6: Development cost per MW | B6: =Assumptions!$B$7 -> 13000000
A7: Expected stabilized yield on cost | B7: =Assumptions!$B$11 -> 0.119
A8: Unlevered IRR | B8: ='Cash Flow & Returns'!B17 -> 0.18480469
A9: Levered IRR | B9: ='Cash Flow & Returns'!B18 -> 0.29084583
A10: Unlevered NPV (at WACC) | B10: ='Cash Flow & Returns'!B19 -> 3.7899463e+08
A11: Approx. payback period (years) | B11: ='Cash Flow & Returns'!B20 -> 4.3333333
A12: Minimum DSCR (Years 1-5) | B12: =MIN('Cash Flow & Returns'!C10:G10) -> 1.5735537
A14: Recommendation & Key Risks
A15: ● Base case unlevered IRR clears WACC, supporting proceeding to full underwriting, subject to lender term sheet confirmation.
A16: ● DSCR stays above 1.5x through the ramp period at the assumed 55% loan to cost, providing headroom against a slower lease up.
A17: ● Primary risk: lease up pace. A 2 quarter delay in reaching 85% stabilization compresses IRR materially, see Sensitivity tab.
A18: ● Primary risk: exit cap rate expansion. Every 50 bps of cap rate expansion at exit reduces terminal value and unlevered IRR, see Sensitivity tab.
A19: ● Cost of debt and WACC are general market assumptions, not company sourced. Confirm against live lender quotes before final underwriting.
